odoo8_addon_contract_account_banking_mandate-8.0.1.0.0-py2.7-nspkg.pth
odoo_addons/contract_account_banking_mandate/__openerp__.py
odoo_addons/contract_account_banking_mandate/__init__.py
odoo_addons/contract_account_banking_mandate/README.rst
odoo_addons/contract_account_banking_mandate/models/__init__.py
odoo_addons/contract_account_banking_mandate/models/account_analytic_account.py
odoo_addons/contract_account_banking_mandate/i18n/es.po
odoo_addons/contract_account_banking_mandate/views/contract_view.xml
odoo_addons/contract_account_banking_mandate/tests/contract_account_banking_mandate.yml
odoo8_addon_contract_account_banking_mandate-8.0.1.0.0.dist-info/top_level.txt
odoo8_addon_contract_account_banking_mandate-8.0.1.0.0.dist-info/WHEEL
odoo8_addon_contract_account_banking_mandate-8.0.1.0.0.dist-info/RECORD
odoo8_addon_contract_account_banking_mandate-8.0.1.0.0.dist-info/metadata.json
odoo8_addon_contract_account_banking_mandate-8.0.1.0.0.dist-info/DESCRIPTION.rst
odoo8_addon_contract_account_banking_mandate-8.0.1.0.0.dist-info/METADATA
odoo8_addon_contract_account_banking_mandate-8.0.1.0.0.dist-info/namespace_packages.txt
