Metadata-Version: 2.0
Name: odoo8-addon-contract-account-banking-mandate
Version: 8.0.1.0.0
Summary: Add banking mandate field to contracts for their invoices
Home-page: http://www.binovo.es
Author: UNKNOWN
Author-email: UNKNOWN
License: UNKNOWN
Platform: UNKNOWN
Requires-Dist: odoo (<9.0a,>=8.0a)
Requires-Dist: odoo8-addon-account-banking-mandate
Classifier: Programming Language :: Python :: 2.7
Classifier: Framework :: Odoo
